bionemo_noodles-0.1.2.dist-info/METADATA
bionemo_noodles-0.1.2.dist-info/WHEEL
bionemo_noodles-0.1.2.dist-info/licenses/LICENSE
bionemo/noodles/nvfaidx.py
bionemo/noodles/__init__.py
bionemo/noodles_fasta_wrapper.cpython-312-x86_64-linux-gnu.so
bionemo_noodles-0.1.2.dist-info/RECORD
