Metadata-Version: 2.4
Name: bionemo-noodles
Version: 0.1.2
Requires-Dist: bionemo-core
Requires-Dist: pyfaidx
Requires-Dist: torch ; extra == 'test'
Provides-Extra: test
License-File: LICENSE
Summary: Python wrapper around [noodles](https://github.com/zaeleus/noodles).
Author-email: BioNeMo Team <bionemofeedback@nvidia.com>
Requires-Python: >=3.10
